LICENSE
MANIFEST.in
README.md
requirements.txt
setup.py
django_lazypage.egg-info/PKG-INFO
django_lazypage.egg-info/SOURCES.txt
django_lazypage.egg-info/dependency_links.txt
django_lazypage.egg-info/requires.txt
django_lazypage.egg-info/top_level.txt
lazypage/__init__.py
lazypage/admin.py
lazypage/apps.py
lazypage/decorators.py
lazypage/execution.py
lazypage/lazy_celery.py
lazypage/models.py
lazypage/settings.py
lazypage/tasks.py
lazypage/urls.py
lazypage/utils.py
lazypage/views.py
lazypage/migrations/0001_initial.py
lazypage/migrations/__init__.py
lazypage/templates/lazypage/loading.html