Metadata-Version: 2.1
Name: django-lazypage
Version: 0.2.7
Summary: django 页面异步加载解决方案
Home-page: https://github.com/taojy123/django-lazypage
Author: tao.py
Author-email: taojy123@163.com
Maintainer: tao.py
Maintainer-email: taojy123@163.com
License: MIT License
Platform: all
Classifier: Programming Language :: Python
Classifier: Programming Language :: Python :: 2
Classifier: Programming Language :: Python :: 3
Classifier: Framework :: Django
